setup.py
uniopen/__init__.py
uniopen.egg-info/PKG-INFO
uniopen.egg-info/SOURCES.txt
uniopen.egg-info/dependency_links.txt
uniopen.egg-info/not-zip-safe
uniopen.egg-info/requires.txt
uniopen.egg-info/top_level.txt
uniopen/tests/__init__.py