Metadata-Version: 1.0
Name: uniopen
Version: 1.0.2
Summary: Universal File Opener
Home-page: http://bfaludi.com
Author: Bence Faludi
Author-email: bence@ozmo.hu
License: GPL
Platform: UNKNOWN
